caldav_server_tester/__init__.py
caldav_server_tester/caldav_server_tester.py
caldav_server_tester/caldav_server_tester_old.py
caldav_server_tester/checker.py
caldav_server_tester/checks.py
caldav_server_tester/checks_base.py
caldav_server_tester-0.1.0.dist-info/METADATA
caldav_server_tester-0.1.0.dist-info/WHEEL
caldav_server_tester-0.1.0.dist-info/entry_points.txt
caldav_server_tester-0.1.0.dist-info/licenses/agpl-3.0.md
caldav_server_tester-0.1.0.dist-info/RECORD
