Metadata-Version: 2.4
Name: caldav-server-tester
Version: 0.1.0
Summary: CalDAV Server Checker - checking a CalDAV server for compatibility issues
License-Expression: AGPL-3.0-or-later
License-File: agpl-3.0.md
Author: Tobias Brox
Author-email: tobias@redpill-linpro.com
Requires-Python: >=3.13
Classifier: Programming Language :: Python :: 3
Classifier: Programming Language :: Python :: 3.13
Classifier: Programming Language :: Python :: 3.14
Requires-Dist: caldav (>=2.1.0)
